mosaia/__init__.py
mosaia/api_client.py
mosaia/base_api.py
mosaia/client.py
mosaia/config.py
mosaia/py.typed
mosaia/types.py
mosaia/auth/__init__.py
mosaia/auth/auth.py
mosaia/auth/oauth.py
mosaia/collections/__init__.py
mosaia/collections/agent_groups.py
mosaia/collections/agents.py
mosaia/collections/app_bots.py
mosaia/collections/apps.py
mosaia/collections/base_collection.py
mosaia/collections/clients.py
mosaia/collections/models.py
mosaia/collections/org_users.py
mosaia/collections/organizations.py
mosaia/collections/tools.py
mosaia/collections/users.py
mosaia/functions/__init__.py
mosaia/functions/base_functions.py
mosaia/functions/chat.py
mosaia/functions/completions.py
mosaia/models/__init__.py
mosaia/models/agent.py
mosaia/models/agent_group.py
mosaia/models/app.py
mosaia/models/app_bot.py
mosaia/models/base.py
mosaia/models/client.py
mosaia/models/model.py
mosaia/models/org_user.py
mosaia/models/organization.py
mosaia/models/session.py
mosaia/models/tool.py
mosaia/models/user.py
mosaia/utils/__init__.py
mosaia/utils/api_client.py
mosaia/utils/helpers.py
mosaia-0.0.4.dist-info/licenses/LICENSE
mosaia-0.0.4.dist-info/METADATA
mosaia-0.0.4.dist-info/WHEEL
mosaia-0.0.4.dist-info/top_level.txt
mosaia-0.0.4.dist-info/RECORD
