Metadata-Version: 2.4
Name: mosaia
Version: 0.0.4
Summary: A comprehensive Python SDK for the Mosaia AI platform
Home-page: https://github.com/mosaia-development/mosaia-python-sdk
Author: Mosaia Team
Author-email: Mosaia Team <support@mosaia.ai>
Maintainer-email: Mosaia Team <support@mosaia.ai>
License: MIT
Project-URL: Homepage, https://github.com/mosaia-development/mosaia-python-sdk
Project-URL: Documentation, https://docs.mosaia.ai/python-sdk
Project-URL: Repository, https://github.com/mosaia-development/mosaia-python-sdk
Project-URL: Bug Tracker, https://github.com/mosaia-development/mosaia-python-sdk/issues
Keywords: ai,artificial intelligence,api,sdk,mosaia,agents,tools,applications
Classifier: Development Status :: 4 - Beta
Classifier: Intended Audience :: Developers
Classifier: License :: OSI Approved :: MIT License
Classifier: Operating System :: OS Independent
Classifier: Programming Language :: Python :: 3
Classifier: Programming Language :: Python :: 3.8
Classifier: Programming Language :: Python :: 3.9
Classifier: Programming Language :: Python :: 3.10
Classifier: Programming Language :: Python :: 3.11
Classifier: Programming Language :: Python :: 3.12
Classifier: Topic :: Software Development :: Libraries :: Python Modules
Classifier: Topic :: Internet :: WWW/HTTP :: Dynamic Content
Classifier: Topic :: Scientific/Engineering :: Artificial Intelligence
Requires-Python: >=3.8
License-File: LICENSE
Requires-Dist: requests>=2.25.0
Requires-Dist: aiohttp>=3.8.0
Requires-Dist: dataclasses-json>=0.5.0; python_version < "3.7"
Requires-Dist: python-dotenv>=0.19.0
Provides-Extra: dev
Requires-Dist: pytest>=7.0.0; extra == "dev"
Requires-Dist: pytest-asyncio>=0.21.0; extra == "dev"
Requires-Dist: pytest-cov>=4.0.0; extra == "dev"
Requires-Dist: black>=22.0.0; extra == "dev"
Requires-Dist: isort>=5.10.0; extra == "dev"
Requires-Dist: flake8>=5.0.0; extra == "dev"
Requires-Dist: mypy>=1.0.0; extra == "dev"
Requires-Dist: build>=0.10.0; extra == "dev"
Requires-Dist: twine>=4.0.0; extra == "dev"
Dynamic: author
Dynamic: home-page
Dynamic: license-file
Dynamic: requires-python
